Workbook

Sheet SUPUESTOS
A1: PLANTILLA DE VALUACIÓN DCF - SUPUESTOS GENERALES
B3: Concepto | C3: Valor
B4: Empresa | C4: Valor, S.A. de C.V.
B5: Fecha de Valuación | C5: 45658
B6: Moneda | C6: MXN
A8: CRECIMIENTO DE INGRESOS
B9: Concepto | C9: Año -1 | D9: Año 0 | E9: Año 1 | F9: Año 2 | G9: Año 3 | H9: Año 4 | I9: Año 5
B10: Tasa de Crecimiento | C10: 0.163 | D10: 0.19 | E10: 0.05 | F10: 0.05 | G10: 0.05 | H10: 0.05 | I10: 0.05
A12: ESTRUCTURA DE COSTOS (% de Ingresos)
B13: Concepto | C13: Año -1 | D13: Año 0 | E13: Año 1 | F13: Año 2 | G13: Año 3 | H13: Año 4 | I13: Año 5
B14: Costo Directo | C14: 0.636 | D14: 0.636 | E14: 0.636 | F14: 0.631 | G14: 0.631 | H14: 0.626 | I14: 0.626
B15: Gastos de Venta | C15: 0.235 | D15: 0.242 | E15: 0.242 | F15: 0.242 | G15: 0.242 | H15: 0.242 | I15: 0.242
B16: Gastos Administrativos | C16: 0.019 | D16: 0.018 | E16: 0.019 | F16: 0.019 | G16: 0.019 | H16: 0.019 | I16: 0.019
B17: Depreciación y Amortización (D&A) | C17: 0.026 | D17: 0.025 | E17: 0.025 | F17: 0.025 | G17: 0.025 | H17: 0.025 | I17: 0.025
A19: DÍAS DE CAPITAL DE TRABAJO
B20: Concepto | C20: Valor
B21: Días Cuentas por Cobrar (CxC) | C21: 45
B22: Días Inventario | C22: 20
B23: Días Cuentas por Pagar (CxP) | C23: 69
A25: TASAS E IMPUESTOS
B26: Concepto | C26: Valor
B27: ISR + PTU | C27: 0.008
B28: CapEx (% de Ingresos) | C28: 0.025
A31: WACC Y VALOR TERMINAL
B32: Concepto | C32: Valor
B33: WACC (Costo Promedio Ponderado de Capital) | C33: 0.175
B34: Crecimiento Terminal (Perpetuidad) | C34: 0
B35: Método de Valor Terminal | C35: Growth
A37: DATOS DE BALANCE GENERAL
B38: Concepto | C38: Valor
B39: Deuda Total | C39: 54739
B40: Efectivo y Equivalentes | C40: 7411
B41: Capital Contable | C41: 218956

Sheet CAPITAL_TRABAJO
A1: DETALLE DE CAPITAL DE TRABAJO (Miles de MXN)
B2: Concepto | C2: Año -1 | D2: Año 0 | E2: Año 1 | F2: Año 2 | G2: Año 3 | H2: Año 4 | I2: Año 5
B4: Cuentas por Cobrar (CxC) | C4: ='SUPUESTOS'!$C$21/365*'ESTADO_RESULTADOS'!C3 | D4: ='SUPUESTOS'!$C$21/365*'ESTADO_RESULTADOS'!D3 | E4: ='SUPUESTOS'!$C$21/365*'ESTADO_RESULTADOS'!E3 | F4: ='SUPUESTOS'!$C$21/365*'ESTADO_RESULTADOS'!F3 | G4: ='SUPUESTOS'!$C$21/365*'ESTADO_RESULTADOS'!G3 | H4: ='SUPUESTOS'!$C$21/365*'ESTADO_RESULTADOS'!H3 | I4: ='SUPUESTOS'!$C$21/365*'ESTADO_RESULTADOS'!I3
B6: Inventario | C6: ='SUPUESTOS'!$C$22/365*'ESTADO_RESULTADOS'!C6 | D6: ='SUPUESTOS'!$C$22/365*'ESTADO_RESULTADOS'!D6 | E6: ='SUPUESTOS'!$C$22/365*'ESTADO_RESULTADOS'!E6 | F6: ='SUPUESTOS'!$C$22/365*'ESTADO_RESULTADOS'!F6 | G6: ='SUPUESTOS'!$C$22/365*'ESTADO_RESULTADOS'!G6 | H6: ='SUPUESTOS'!$C$22/365*'ESTADO_RESULTADOS'!H6 | I6: ='SUPUESTOS'!$C$22/365*'ESTADO_RESULTADOS'!I6
B8: Cuentas por Pagar (CxP) | C8: ='SUPUESTOS'!$C$23/365*('ESTADO_RESULTADOS'!C6+'ESTADO_RESULTADOS'!C7+'ESTADO_RESULTADOS'!C8) | D8: ='SUPUESTOS'!$C$23/365*('ESTADO_RESULTADOS'!D6+'ESTADO_RESULTADOS'!D7+'ESTADO_RESULTADOS'!D8) | E8: ='SUPUESTOS'!$C$23/365*('ESTADO_RESULTADOS'!E6+'ESTADO_RESULTADOS'!E7+'ESTADO_RESULTADOS'!E8) | F8: ='SUPUESTOS'!$C$23/365*('ESTADO_RESULTADOS'!F6+'ESTADO_RESULTADOS'!F7+'ESTADO_RESULTADOS'!F8) | G8: ='SUPUESTOS'!$C$23/365*('ESTADO_RESULTADOS'!G6+'ESTADO_RESULTADOS'!G7+'ESTADO_RESULTADOS'!G8) | H8: ='SUPUESTOS'!$C$23/365*('ESTADO_RESULTADOS'!H6+'ESTADO_RESULTADOS'!H7+'ESTADO_RESULTADOS'!H8) | I8: ='SUPUESTOS'!$C$23/365*('ESTADO_RESULTADOS'!I6+'ESTADO_RESULTADOS'!I7+'ESTADO_RESULTADOS'!I8)
B10: Working Capital (CxC + Inv - CxP) | C10: =C4+C6-C8 | D10: =D4+D6-D8 | E10: =E4+E6-E8 | F10: =F4+F6-F8 | G10: =G4+G6-G8 | H10: =H4+H6-H8 | I10: =I4+I6-I8
B12: Δ Working Capital | C12: 0 | D12: =D10-C10 | E12: =E10-D10 | F12: =F10-E10 | G12: =G10-F10 | H12: =H10-G10 | I12: =I10-H10

Sheet ESTADO_RESULTADOS
A1: ESTADO DE RESULTADOS PROYECTADO (Miles de MXN)
B2: Concepto | C2: Año -1 | D2: Año 0 | E2: Año 1 | F2: Año 2 | G2: Año 3 | H2: Año 4 | I2: Año 5
B3: Ingresos | C3: 622590 | D3: 741120 | E3: =D3*(1+'SUPUESTOS'!$E$10) | F3: =E3*(1+'SUPUESTOS'!$F$10) | G3: =F3*(1+'SUPUESTOS'!$G$10) | H3: =G3*(1+'SUPUESTOS'!$H$10) | I3: =H3*(1+'SUPUESTOS'!$I$10)
B4: Crecimiento % | C4: 0.163 | D4: ='SUPUESTOS'!$D$10 | E4: ='SUPUESTOS'!$E$10 | F4: ='SUPUESTOS'!$F$10 | G4: ='SUPUESTOS'!$G$10 | H4: ='SUPUESTOS'!$H$10 | I4: ='SUPUESTOS'!$I$10
B6: Costo Directo | C6: 395967.24 | D6: 471352.32 | E6: =E3*'SUPUESTOS'!$C$14 | F6: =F3*'SUPUESTOS'!$C$14 | G6: =G3*'SUPUESTOS'!$C$14 | H6: =H3*'SUPUESTOS'!$C$14 | I6: =I3*'SUPUESTOS'!$C$14
B7: Gastos de Venta | C7: 146308.65 | D7: 179351.04 | E7: =E3*'SUPUESTOS'!$C$15 | F7: =F3*'SUPUESTOS'!$C$15 | G7: =G3*'SUPUESTOS'!$C$15 | H7: =H3*'SUPUESTOS'!$C$15 | I7: =I3*'SUPUESTOS'!$C$15
B8: Gastos Administrativos | C8: 11829.21 | D8: 13340.16 | E8: =E3*'SUPUESTOS'!$C$16 | F8: =F3*'SUPUESTOS'!$C$16 | G8: =G3*'SUPUESTOS'!$C$16 | H8: =H3*'SUPUESTOS'!$C$16 | I8: =I3*'SUPUESTOS'!$C$16
B9: Depreciación y Amortización | C9: 16187.34 | D9: 18528 | E9: =E3*'SUPUESTOS'!$C$17 | F9: =F3*'SUPUESTOS'!$C$17 | G9: =G3*'SUPUESTOS'!$C$17 | H9: =H3*'SUPUESTOS'!$C$17 | I9: =I3*'SUPUESTOS'!$C$17
B11: Total Costos y Gastos | C11: =SUM(C6:C9) | D11: =SUM(D6:D9) | E11: =SUM(E6:E9) | F11: =SUM(F6:F9) | G11: =SUM(G6:G9) | H11: =SUM(H6:H9) | I11: =SUM(I6:I9)
B13: Utilidad de Operación (EBIT) | C13: =C3-C11 | D13: =D3-D11 | E13: =E3-E11 | F13: =F3-F11 | G13: =G3-G11 | H13: =H3-H11 | I13: =I3-I11
B14: Margen EBIT % | C14: =C13/C3 | D14: =D13/D3 | E14: =E13/E3 | F14: =F13/F3 | G14: =G13/G3 | H14: =H13/H3 | I14: =I13/I3
B16: ISR + PTU | C16: =C13*'SUPUESTOS'!$C$27 | D16: =D13*'SUPUESTOS'!$C$27 | E16: =E13*'SUPUESTOS'!$C$27 | F16: =F13*'SUPUESTOS'!$C$27 | G16: =G13*'SUPUESTOS'!$C$27 | H16: =H13*'SUPUESTOS'!$C$27 | I16: =I13*'SUPUESTOS'!$C$27
B18: NOPAT (Utilidad Neta Operativa) | C18: =C13-C16 | D18: =D13-D16 | E18: =E13-E16 | F18: =F13-F16 | G18: =G13-G16 | H18: =H13-H16 | I18: =I13-I16
B19: Margen Neto % | C19: =C18/C3 | D19: =D18/D3 | E19: =E18/E3 | F19: =F18/F3 | G19: =G18/G3 | H19: =H18/H3 | I19: =I18/I3
B21: Utilidad Neta | C21: =C18 | D21: =D18 | E21: =E18 | F21: =F18 | G21: =G18 | H21: =H18 | I21: =I18

Sheet FLUJO_EFECTIVO
A1: FLUJO DE CAJA LIBRE PROYECTADO (Miles de MXN)
B2: Concepto | C2: Año -1 | D2: Año 0 | E2: Año 1 | F2: Año 2 | G2: Año 3 | H2: Año 4 | I2: Año 5
B3: NOPAT | C3: ='ESTADO_RESULTADOS'!C18 | D3: ='ESTADO_RESULTADOS'!D18 | E3: ='ESTADO_RESULTADOS'!E18 | F3: ='ESTADO_RESULTADOS'!F18 | G3: ='ESTADO_RESULTADOS'!G18 | H3: ='ESTADO_RESULTADOS'!H18 | I3: ='ESTADO_RESULTADOS'!I18
B5: (+) Depreciación y Amortización | C5: ='ESTADO_RESULTADOS'!C9 | D5: ='ESTADO_RESULTADOS'!D9 | E5: ='ESTADO_RESULTADOS'!E9 | F5: ='ESTADO_RESULTADOS'!F9 | G5: ='ESTADO_RESULTADOS'!G9 | H5: ='ESTADO_RESULTADOS'!H9 | I5: ='ESTADO_RESULTADOS'!I9
B7: (-) Δ Capital de Trabajo | C7: ='CAPITAL_TRABAJO'!C12 | D7: ='CAPITAL_TRABAJO'!D12 | E7: ='CAPITAL_TRABAJO'!E12 | F7: ='CAPITAL_TRABAJO'!F12 | G7: ='CAPITAL_TRABAJO'!G12 | H7: ='CAPITAL_TRABAJO'!H12 | I7: ='CAPITAL_TRABAJO'!I12
B9: (-) CapEx | C9: ='ESTADO_RESULTADOS'!C3*'SUPUESTOS'!$C$28 | D9: ='ESTADO_RESULTADOS'!D3*'SUPUESTOS'!$C$28 | E9: ='ESTADO_RESULTADOS'!E3*'SUPUESTOS'!$C$28 | F9: ='ESTADO_RESULTADOS'!F3*'SUPUESTOS'!$C$28 | G9: ='ESTADO_RESULTADOS'!G3*'SUPUESTOS'!$C$28 | H9: ='ESTADO_RESULTADOS'!H3*'SUPUESTOS'!$C$28 | I9: ='ESTADO_RESULTADOS'!I3*'SUPUESTOS'!$C$28
B11: Flujo de Caja Libre (FCF) | C11: =C3+C5-C7-C9 | D11: =D3+D5-D7-D9 | E11: =E3+E5-E7-E9 | F11: =F3+F5-F7-F9 | G11: =G3+G5-G7-G9 | H11: =H3+H5-H7-H9 | I11: =I3+I5-I7-I9
B13: Factor de Descuento (WACC) | C13: 1 | D13: 1 | E13: =1/(1+'SUPUESTOS'!$C$33)^1 | F13: =1/(1+'SUPUESTOS'!$C$33)^2 | G13: =1/(1+'SUPUESTOS'!$C$33)^3 | H13: =1/(1+'SUPUESTOS'!$C$33)^4 | I13: =1/(1+'SUPUESTOS'!$C$33)^5
B15: FCF Descontado | C15: =C11*C13 | D15: =D11*D13 | E15: =E11*E13 | F15: =F11*F13 | G15: =G11*G13 | H15: =H11*H13 | I15: =I11*I13
B17: Valor Terminal (Perpetuidad) | C17: =IF('SUPUESTOS'!$C$35="Growth",I11*(1+'SUPUESTOS'!$C$34)/('SUPUESTOS'!$C$33-'SUPUESTOS'!$C$34),IF('SUPUESTOS'!$C$35="Zero",I11/'SUPUESTOS'!$C$33,0))
B19: Valor Terminal Descontado | C19: =C17*I13

Sheet VALUACION
A1: RESUMEN DE VALUACIÓN (Miles de MXN)
B3: Concepto | C3: Valor
B5: Enterprise Value (EV) | C5: =SUM('FLUJO_EFECTIVO'!E15:I15)+'FLUJO_EFECTIVO'!C19
B7: (-) Deuda Total | C7: ='SUPUESTOS'!$C$39
B9: (+) Efectivo y Equivalentes | C9: ='SUPUESTOS'!$C$40
B11: Valor del Equity | C11: =C5-C7+C9
A14: MÚLTIPLOS DE VALUACIÓN
B15: Indicador | C15: Valor
B17: EV / Ventas Año 0 | C17: =C5/'ESTADO_RESULTADOS'!D3
B19: EV / EBITDA Año 0 | C19: =C5/('ESTADO_RESULTADOS'!D13+'ESTADO_RESULTADOS'!D9)
B21: Valor / Capital Contable | C21: =C11/'SUPUESTOS'!$C$41
